sounds/__init__.py
sounds/auth.py
sounds/base.py
sounds/client.py
sounds/constants.py
sounds/exceptions.py
sounds/icons/dark/categories.png
sounds/icons/dark/collections.png
sounds/icons/dark/continue.png
sounds/icons/dark/editorial.png
sounds/icons/dark/episodes.png
sounds/icons/dark/featured.png
sounds/icons/dark/latest.png
sounds/icons/dark/listen_live.png
sounds/icons/dark/music.png
sounds/icons/dark/my_location.png
sounds/icons/dark/my_sounds.png
sounds/icons/dark/news.png
sounds/icons/dark/podcasts.png
sounds/icons/dark/recent.png
sounds/icons/dark/speech.png
sounds/icons/light/categories.png
sounds/icons/light/collections.png
sounds/icons/light/continue.png
sounds/icons/light/editorial.png
sounds/icons/light/episodes.png
sounds/icons/light/featured.png
sounds/icons/light/latest.png
sounds/icons/light/listen_live.png
sounds/icons/light/music.png
sounds/icons/light/my_location.png
sounds/icons/light/my_sounds.png
sounds/icons/light/news.png
sounds/icons/light/podcasts.png
sounds/icons/light/speech.png
sounds/icons/solid/categories.png
sounds/icons/solid/collections.png
sounds/icons/solid/continue.png
sounds/icons/solid/editorial.png
sounds/icons/solid/episodes.png
sounds/icons/solid/featured.png
sounds/icons/solid/latest.png
sounds/icons/solid/listen_live.png
sounds/icons/solid/music.png
sounds/icons/solid/my_location.png
sounds/icons/solid/my_sounds.png
sounds/icons/solid/news.png
sounds/icons/solid/podcasts.png
sounds/icons/solid/recent.png
sounds/icons/solid/speech.png
sounds/models.py
sounds/parser.py
sounds/personal.py
sounds/schedules.py
sounds/sounds_types.py
sounds/stations.py
sounds/streaming.py
sounds/utils.py
auntie_sounds-1.1.7.dist-info/WHEEL
auntie_sounds-1.1.7.dist-info/METADATA
auntie_sounds-1.1.7.dist-info/RECORD
