Metadata-Version: 2.3
Name: auntie-sounds
Version: 1.1.7
Summary: A library for interacting with BBC Radio stations and streams
Requires-Dist: aiohappyeyeballs>=2.6.1
Requires-Dist: aiohttp>=3.12.13
Requires-Dist: aiosignal>=1.4.0
Requires-Dist: appdirs>=1.4.4
Requires-Dist: attrs>=25.3.0
Requires-Dist: beautifulsoup4>=4.13.4
Requires-Dist: colorlog>=6.9.0
Requires-Dist: frozenlist>=1.7.0
Requires-Dist: idna>=3.10
Requires-Dist: multidict>=6.6.3
Requires-Dist: propcache>=0.3.2
Requires-Dist: pytz>=2025.2
Requires-Dist: soupsieve>=2.7
Requires-Dist: typing-extensions>=4.14.1
Requires-Dist: yarl>=1.20.1
Requires-Python: >=3.12
